{
    "s":[
        {    
            "name": "Dream Sequins®",
            "artist":"Nmesh",
            "image": "https://f4.bcbits.com/img/a2617555620_10.jpg",
            "description": "This is that record that got me into vaporwave, and it is the very best.",
            "bandcamp": "https://nmesh.bandcamp.com/album/dream-sequins"
        },
        {
            "name":"ロ​ス​ト​エ​デ​ン​へ​の​パ​ス (The path to lost eden)",
            "artist":"Nmesh and t e l e p a t h テレパシー能力者",
            "image":"https://f4.bcbits.com/img/a2129077846_10.jpg",
            "description":"Not a single track is a miss. Both artists put their best works ever on here.",
            "bandcamp":"https://nmesh.bandcamp.com/album/--2"
        },
        {
            "name": "I'll Try Living Like This",
            "artist":"death's dynamic shroud.wmv",
            "image":"https://f4.bcbits.com/img/a0102733853_10.jpg",
            "description": "Haunting, soothing, terrifying and sad at the same time. Nothing will ever be similar to this masterpiece.",
            "bandcamp": "https://deathsdynamicshroud.bandcamp.com/album/ill-try-living-like-this"
        },
        {
            "name":"大​理​石​の​フ​ァ​ン​タ​ジ​ー (Marble Fantasy)",
            "artist":"Haircuts for Men",
            "image":"https://f4.bcbits.com/img/a2921127091_10.jpg",
            "description":"Idk man this record slaps so fucking hard.",
            "bandcamp":"https://haircutsformen.bandcamp.com/album/--3"
        },
        {
            "name":"Rain Temple",
            "artist":"2814",
            "image":"https://f4.bcbits.com/img/a0901283591_10.jpg",
            "description":"This is just amazing. No further comment nessecary.",
            "bandcamp":"https://dreamcatalogue.bandcamp.com/album/rain-temple"
        },
        {
            "name":"The city is my friend",
            "artist":"Remember",
            "image":"https://f4.bcbits.com/img/a1106418967_10.jpg",
            "description":"Masterpiece. Definitely better than Birth of a new Day.",
            "bandcamp":"https://dreamcatalogue.bandcamp.com/album/the-city-is-my-friend"
        },
        {
            "name":"L.Y.F",
            "artist":"Hong Kong Express",
            "image":"https://f4.bcbits.com/img/a3072806146_10.jpg",
            "description":"Super nice. Some tracks are just fantastic. Personal favorite is 'Changing Trains'.",
            "bandcamp":"https://dreamcatalogue.bandcamp.com/album/l-y-f"
        },
        {
            "name":"REMNANTS",
            "artist":"Oblique Occasions",
            "image":"https://f4.bcbits.com/img/a3144491188_10.jpg",
            "description":"My god this record is nice. Bimodal is my favorite Oblique Occasions track.",
            "bandcamp":"https://obliqueoccasions.bandcamp.com/album/remnants"
        }
    ],
    "a": [
        {
            "name": "Nu.wav Hallucinations",
            "artist":"Nmesh",
            "image": "https://f4.bcbits.com/img/a2049145046_10.jpg",
            "description": "Great, but Dream Sequins® is better. I own this on vinyl.",
            "bandcamp": "https://nmesh.bandcamp.com/album/nu-wav-hallucinations"
        },
        {
            "name": "NEWS AT 11",
            "artist": "猫 シ Corp.",
            "image": "https://f4.bcbits.com/img/a1964377693_10.jpg",
            "description":"The best from catsystemcorp. This is a very special concept album.",
            "bandcamp":"https://catsystemcorp.bandcamp.com/album/news-at-11-remastered"
        },
        {
            "name":"痛​み​の​永​遠 (Eternity of Pain)",
            "artist":"Macroblank",
            "image":"https://f4.bcbits.com/img/a1957926096_10.jpg",
            "description":"The best that macroblank ever put out. So happy I have the vinyl.",
            "bandcamp":"https://macroblank.bandcamp.com/album/--21"
        },
        {
            "name":"ルートバックホーム (Route Back Home)",
            "artist":"Remember",
            "image":"https://f4.bcbits.com/img/a3675313495_10.jpg",
            "description":"Just great. I love how it slowly builds up the music throughout the entire record.",
            "bandcamp":"https://dreamcatalogue.bandcamp.com/album/--22"
        },
        {
            "name": "新​し​い​日​の​誕​生 (Birth of a new Day)",
            "artist":"2814",
            "image":"https://f4.bcbits.com/img/a4099353330_10.jpg",
            "description":"Slightly overrated, still amazing. So happy to own on vinyl!",
            "bandcamp": "https://dreamcatalogue.bandcamp.com/album/--18"
        },
        {
            "name":"Ibis valley",
            "artist":"Macroblank",
            "image":"https://f4.bcbits.com/img/a1623583478_10.jpg",
            "description":"Excellent. Barber Beats/Late Night Lofi is a very good combination.",
            "bandcamp":"https://macroblank.bandcamp.com/album/ibis-valley"
        },
        {
            "name":"Pharma",
            "artist":"Nmesh",
            "image":"https://f4.bcbits.com/img/a3973099227_10.jpg",
            "description":"Words cannot describe what this record is. Just know it's good.",
            "bandcamp":"https://orangemilkrecords.bandcamp.com/album/pharma"
        },
        {
            "name":"Sable Covenant",
            "artist":"Oblique Occasions",
            "image":"https://f4.bcbits.com/img/a0409101075_10.jpg",
            "description":"Just some very nice and chill barber beats. Nothing new is best track.",
            "bandcamp":"https://obliqueoccasions.bandcamp.com/album/sable-covenant"
        },
        {
            "name":"孤​独​な​人​々​の​た​め​の​内​省​的​な​音​楽",
            "artist":"Monodrone",
            "image":"https://f4.bcbits.com/img/a0607810724_10.jpg",
            "description":"(Introspective Music For Lonely People). Overdose in paradise is amazing. The rest is also quality.",
            "bandcamp":"https://i-am-monodrone.bandcamp.com/album/--3"
        }
    ],
    "b": [
        {
            "name":"Cytherea Somniare",
            "artist": "DARKPYRAMID",
            "image":"https://f4.bcbits.com/img/a1814808848_10.jpg",
            "description": "By far my favorite DARKPYRAMID record. It just has a very special mood.",
            "bandcamp": "https://noproblematapes.bandcamp.com/album/cytherea-somniare"
        },
        {
            "name":"Darklife",
            "artist":"death's dynamic shroud",
            "image":"https://f4.bcbits.com/img/a2954521948_10.jpg",
            "description":"So experimental it's impossible to tell what it is. Still not the best dds record though.",
            "bandcamp":"https://deathsdynamicshroud.bandcamp.com/album/darklife-2"
        },
        {
            "name":"200% Electronica",
            "artist":"ESPRIT 空想",
            "image":"https://f4.bcbits.com/img/a2618300680_10.jpg",
            "description":"Actually really good. Criminally underrated.",
            "bandcamp":"https://espritfantasy.bandcamp.com/album/200-electronica"
        },
        {
            "name":"Good Morning America",
            "artist":"猫 シ Corp.",
            "image":"https://f4.bcbits.com/img/a1579131859_10.jpg",
            "description":"Almost as good as NEWS AT 11. Still very special.",
            "bandcamp":"https://catsystemcorp.bandcamp.com/album/good-morning-america"
        },
        {
            "name":"SH40",
            "artist":"Zuwe",
            "image":"https://f4.bcbits.com/img/a0674824177_10.jpg",
            "description":"That first track is perfect. The rest of the record is good, but New Surroundings is the peak.",
            "bandcamp":"https://hiraeth-records.bandcamp.com/album/sh40"
        },
        {
            "name":"A Deep Dive Into The Conflicted and Scared Psyche",
            "artist":"Remember",
            "image":"https://f4.bcbits.com/img/a3190189480_10.jpg",
            "description":"Idk, this record isn't that good, but I keep coming back to it. It is definitely very special.",
            "bandcamp":"https://remember48.bandcamp.com/album/a-deep-dive-into-the-conflicted-and-scared-psyche"
        },
        {
            "name":"Mana Pool",
            "artist":"VAPERROR",
            "image":"https://f4.bcbits.com/img/a3248760326_10.jpg",
            "description":"Classic vaportrap record. I like this more than Blank Banshee 0/1.",
            "bandcamp":"https://vaperror.bandcamp.com/album/mana-pool-2"
        },
        {
            "name":"Perfect world",
            "artist":"Blackbird",
            "image":"https://f4.bcbits.com/img/a2901810953_10.jpg",
            "description":"Pretty good. It isn't as immersive as other dreampunk records, but still, good. I also own the tape.",
            "bandcamp":"https://f0x3r-fennec.bandcamp.com/album/perfect-world"
        },
        {
            "name":"Slide",
            "artist":"George Clanton",
            "image":"https://f4.bcbits.com/img/a3009101780_10.jpg",
            "description":"Better than 100% Electronica. Not really that much to say beyond that.",
            "bandcamp":"https://georgeclanton.bandcamp.com/album/slide"
        }
    ],
    "c": [        
        {
            "name":"VHS LOUNGE",
            "artist":"vcr-classique",
            "image":"https://f4.bcbits.com/img/a0849784418_10.jpg",
            "description":"The perfect late night lofi record for a night walk, I am sure of it.",
            "bandcamp":"https://vcr-classique.bandcamp.com/album/vhs-lounge"
        },
        {
            "name":"Anathema",
            "artist":"Oblique Occasions",
            "image":"https://f4.bcbits.com/img/a3309345917_10.jpg",
            "description":"Definitly quality, just kinda forgettable. ",
            "bandcamp":"https://obliqueoccasions.bandcamp.com/album/anathema"
        },
        {
            "name":"100% Electronica",
            "artist":"George Clanton",
            "image":"https://f4.bcbits.com/img/a1506352382_10.jpg",
            "description":"It's ok. Some tracks are excellent though. (Bleed, It makes the babies want to cry)",
            "bandcamp":"https://georgeclanton.bandcamp.com/album/100-electronica"
        },
        {
            "name":"terminally online",
            "artist":"Oblique Occasions",
            "image":"https://f4.bcbits.com/img/a0820125049_10.jpg",
            "description":"Some heavy bangers on side A, some misses on side B.",
            "bandcamp":"https://obliqueoccasions.bandcamp.com/album/terminally-online"
        },
        {
            "name":"超​越​愛 (beyond love)",
            "artist":"テレヴァペ",
            "image":"https://f4.bcbits.com/img/a1675322589_10.jpg",
            "description":"I dig it. It's a little samy, but still good.",
            "bandcamp":"https://plus100.bandcamp.com/album/-"
        },
        {
            "name":"Time Moved Like It Used To",
            "artist":"Room 208 and Zuwe",
            "image":"https://f4.bcbits.com/img/a3916438107_10.jpg",
            "description":"A little too dubsteppy for me. The tape is gorgeous btw.",
            "bandcamp":"https://noproblematapes.bandcamp.com/album/time-moved-like-it-used-to"
        }

    ],
    "d": [
        {
            "name":"virtua.zip",
            "artist":"ESPRIT 空想",
            "image":"https://f4.bcbits.com/img/a4042324845_10.jpg",
            "description":"Just very short. And some cuts I simply don't like.",
            "bandcamp":"https://espritfantasy.bandcamp.com/album/virtua-zip"
        },
        {
            "name":"2814",
            "artist":"2814",
            "image":"https://f4.bcbits.com/img/a3615920735_10.jpg",
            "description":"It's meh. Nothing special like other 2814 records.",
            "bandcamp":"https://dreamcatalogue.bandcamp.com/album/2814"
        },
        {
            "name":"行​方​不​明 (Unknown)",
            "artist":"Macroblank",
            "image":"https://f4.bcbits.com/img/a2627682117_10.jpg",
            "description":"Severly overrated. Good, just some tracks are really forgettable.",
            "bandcamp":"https://macroblank.bandcamp.com/album/--5"
        }
    ],
    "e": [
        {
            "name": "Floral Shoppe",
            "artist":"Macintosh Plus",
            "image": "https://f4.bcbits.com/img/a4028863981_10.jpg",
            "description": "Just kinda bad. It started the genre sure but it's not that great.",
            "bandcamp": "https://vektroid.bandcamp.com/album/floral-shoppe"
         }
    ]
}
